otelme.py
otelme-0.0.4.dist-info/LICENSE
otelme-0.0.4.dist-info/WHEEL
otelme-0.0.4.dist-info/METADATA
otelme-0.0.4.dist-info/RECORD
